[
  {
    "content": "Phase 1: Получить SMTP playbook через integration_playbook_expert_v2",
    "status": "completed"
  },
  {
    "content": "Phase 1: Получить дизайн-гайдлайны через design_agent",
    "status": "completed"
  },
  {
    "content": "Phase 2: Разработать Backend (API endpoints, SMTP, логика маркировки)",
    "status": "completed"
  },
  {
    "content": "Phase 2: Разработать Frontend (все страницы, формы, компоненты)",
    "status": "completed"
  },
  {
    "content": "Phase 2: Протестировать через testing_agent_v3",
    "status": "completed"
  },
  {
    "content": "Phase 2: Исправить CRITICAL: Contact page - react-input-mask несовместим с React 18",
    "status": "in_progress"
  },
  {
    "content": "Phase 2: Исправить CRITICAL: CheckProduct Step 3 - результат не отображается",
    "status": "pending"
  },
  {
    "content": "Phase 2: Повторное тестирование после исправлений",
    "status": "pending"
  },
  {
    "content": "Phase 3: Финальная доставка",
    "status": "pending"
  }
]